monotonicnetworks/LipschitzMonotonicNetwork.py
monotonicnetworks/__init__.py
monotonicnetworks/functional.py
monotonicnetworks/group.py
monotonicnetworks/tests.py
monotonicnetworks-1.5.0.dist-info/METADATA
monotonicnetworks-1.5.0.dist-info/WHEEL
monotonicnetworks-1.5.0.dist-info/top_level.txt
monotonicnetworks-1.5.0.dist-info/RECORD
